django_pay2/__init__.py
django_pay2/admin.py
django_pay2/apps.py
django_pay2/contrib/rest_framework/serializers.py
django_pay2/create_payment.py
django_pay2/exceptions.py
django_pay2/migrations/0001_initial.py
django_pay2/migrations/0002_payment_payment_system.py
django_pay2/migrations/__init__.py
django_pay2/models.py
django_pay2/payment_methods.py
django_pay2/providers/__init__.py
django_pay2/providers/base.py
django_pay2/providers/coinpayments/__init__.py
django_pay2/providers/coinpayments/api.py
django_pay2/providers/coinpayments/payment_system.py
django_pay2/providers/coinpayments/serializers.py
django_pay2/providers/coinpayments/urls.py
django_pay2/providers/coinpayments/views.py
django_pay2/providers/free_kassa/__init__.py
django_pay2/providers/free_kassa/api.py
django_pay2/providers/free_kassa/payment_system.py
django_pay2/providers/free_kassa/serializers.py
django_pay2/providers/free_kassa/services.py
django_pay2/providers/free_kassa/urls.py
django_pay2/providers/free_kassa/views.py
django_pay2/providers/payeer/__init__.py
django_pay2/providers/payeer/api.py
django_pay2/providers/payeer/exceptions.py
django_pay2/providers/payeer/functions.py
django_pay2/providers/payeer/payment_system.py
django_pay2/providers/payeer/urls.py
django_pay2/providers/payeer/views.py
django_pay2/providers/perfect_money/__init__.py
django_pay2/providers/perfect_money/api.py
django_pay2/providers/perfect_money/payment_system.py
django_pay2/providers/perfect_money/serializers.py
django_pay2/providers/perfect_money/urls.py
django_pay2/providers/perfect_money/views.py
django_pay2/providers/qiwi/__init__.py
django_pay2/providers/qiwi/api.py
django_pay2/providers/qiwi/payment_system.py
django_pay2/providers/qiwi/serializers.py
django_pay2/providers/qiwi/urls.py
django_pay2/providers/qiwi/views.py
django_pay2/providers/qiwi_kassa/__init__.py
django_pay2/providers/qiwi_kassa/api.py
django_pay2/providers/qiwi_kassa/contants.py
django_pay2/providers/qiwi_kassa/payment_system.py
django_pay2-2.1.0.dist-info/WHEEL
django_pay2-2.1.0.dist-info/METADATA
django_pay2-2.1.0.dist-info/RECORD
