Metadata-Version: 2.1
Name: django-pay2
Version: 2.1.0
Summary: Интеграция платежных систем для Django
Home-page: https://github.com/la1t/django_pay
License: MIT
Author: Anatoly Gusev
Author-email: gusev.tolia@yandex.ru
Requires-Python: >=3.9,<3.10
Classifier: License :: OSI Approved :: MIT License
Classifier: Programming Language :: Python :: 3
Classifier: Programming Language :: Python :: 3.9
Requires-Dist: Django (>=3.2.7,<4.0.0)
Requires-Dist: django-ipware (>=4.0.0,<5.0.0)
Requires-Dist: djangorestframework (>=3.12.4,<4.0.0)
Requires-Dist: requests (>=2.26.0,<3.0.0)
Project-URL: Repository, https://github.com/la1t/django_pay
